workflow/__init__.py
workflow/decoder.py
workflow/workflow-schema.yaml
workflow/workflow_abc.py
workflow/workflow_engine.py
workflow/workflow_validator.py
im_data_manager_workflow_engine-2.0.1.dist-info/LICENSE
im_data_manager_workflow_engine-2.0.1.dist-info/METADATA
im_data_manager_workflow_engine-2.0.1.dist-info/WHEEL
im_data_manager_workflow_engine-2.0.1.dist-info/RECORD
