Metadata-Version: 2.1
Name: im-data-manager-workflow-engine
Version: 2.0.1
Summary: The Data Manager workflow engine, schema and decoder.
Author: Alan Christie
Author-email: achristie@informaticsmatters.com
Requires-Python: >=3.12,<4.0
Classifier: Programming Language :: Python :: 3
Classifier: Programming Language :: Python :: 3.12
Classifier: Programming Language :: Python :: 3.13
Requires-Dist: im-data-manager-job-decoder (>=2.5.0,<3.0.0)
Requires-Dist: im-protobuf (>=8.2.0,<9.0.0)
Requires-Dist: jsonschema (>=4.21.1,<5.0.0)
Requires-Dist: pyyaml (>=5.3.1,<7.0)
